make_future/__init__.py
make_future/make_future.py
make_future-0.2.2.dist-info/METADATA
make_future-0.2.2.dist-info/WHEEL
make_future-0.2.2.dist-info/top_level.txt
make_future-0.2.2.dist-info/RECORD
