Metadata-Version: 2.4
Name: make_future
Version: 0.2.2
Summary: Miniam yet powerful parallelization tool
Author: Vidal Attias
Dynamic: author
Dynamic: summary
